sirius/_sirius.cpython-311-x86_64-linux-gnu.so
sirius/sirius_wrapper.py
sirius/GeneDiversifier/__init__.py
sirius/GeneDiversifier/sequenceDiversifier.py
sirius/GeneDiversifier/data/cho_codon_usage.csv
sirius/GeneDiversifier/data/human_codon_usage.csv
sirius/GeneDiversifier/data/mouse_codon_usage.csv
sirius/build/sirius
sirius/lib/libortools.so.9
sirius/resources/py27_env.tar.xz
sirius_bio-1.7.dist-info/METADATA
sirius_bio-1.7.dist-info/WHEEL
sirius_bio-1.7.dist-info/entry_points.txt
sirius_bio-1.7.dist-info/top_level.txt
sirius_bio-1.7.dist-info/RECORD
sirius_bio-1.7.dist-info/licenses/LICENSE
