Metadata-Version: 2.4
Name: sirius-bio
Version: 1.7
Summary: SIRIUS: maximally divergent synonymous gene design with ILP/CP-SAT core 
Author-email: Amirsadra Mohseni <amohs002@ucr.edu>
License: MIT License
Requires-Python: >=3.10
License-File: LICENSE
Dynamic: license-file
